{
  "date": "2026-06-10",
  "updated": "2026-06-10T15:01:34.553Z",
  "phase": 2,
  "prices": {
    "128940": {
      "price": 411500
    },
    "207940": {
      "price": 1298000
    },
    "247540": {
      "price": 194000
    },
    "267260": {
      "price": 986000
    },
    "329180": {
      "price": 641000
    },
    "373220": {
      "price": 385500
    },
    "bitcoin": {
      "price": 62112,
      "chg": 1.13872
    },
    "ethereum": {
      "price": 1644.55,
      "chg": 0.0725
    },
    "ripple": {
      "price": 1.12,
      "chg": -1.29488
    },
    "solana": {
      "price": 64.81,
      "chg": -0.19859
    },
    "dogecoin": {
      "price": 0.08429,
      "chg": -0.69849
    },
    "chainlink": {
      "price": 7.75,
      "chg": -0.30466
    },
    "ondo-finance": {
      "price": 0.351584,
      "chg": -2.23736
    },
    "aave": {
      "price": 62.56,
      "chg": 2.77909
    },
    "filecoin": {
      "price": 0.751083,
      "chg": -0.92311
    },
    "NVDA": {
      "price": 203.55
    },
    "AMD": {
      "price": 462.65
    },
    "ASML": {
      "price": 1758.15
    },
    "MU": {
      "price": 917.39
    },
    "SNDK": {
      "price": 1696.105
    },
    "IREN": {
      "price": 53.41
    },
    "VRT": {
      "price": 281.84
    },
    "GEV": {
      "price": 873.855
    },
    "CRWV": {
      "price": 96.865
    },
    "NBIS": {
      "price": 220.99
    },
    "ASTS": {
      "price": 88.395
    },
    "RKLB": {
      "price": 105.97
    },
    "TSLA": {
      "price": 385.2
    },
    "CRCL": {
      "price": 81.71
    },
    "COIN": {
      "price": 158.74
    },
    "SMR": {
      "price": 9.695
    },
    "OKLO": {
      "price": 55.73
    },
    "IONQ": {
      "price": 58.265
    },
    "INFQ": {
      "price": 13.931
    },
    "PLTR": {
      "price": 132.53
    },
    "QQQ": {
      "price": 702.29
    },
    "MRVL": {
      "price": 260.2
    },
    "GLW": {
      "price": 172.29
    },
    "CIEN": {
      "price": 436.35
    },
    "COHR": {
      "price": 361.39
    },
    "LITE": {
      "price": 855.545
    },
    "AAOI": {
      "price": 172.185
    },
    "000660": {
      "price": 2048000
    },
    "005930": {
      "price": 302500
    },
    "006400": {
      "price": 496500
    },
    "096770": {
      "price": 103700
    },
    "066970": {
      "price": 126400
    },
    "003670": {
      "price": 187600
    },
    "042660": {
      "price": 110200
    },
    "010140": {
      "price": 26000
    },
    "012450": {
      "price": 1031000
    },
    "064350": {
      "price": 189400
    },
    "079550": {
      "price": 790000
    },
    "034020": {
      "price": 91100
    },
    "052690": {
      "price": 118700
    },
    "068270": {
      "price": 167300
    },
    "009150": {
      "price": 1805000
    },
    "011070": {
      "price": 1090000
    },
    "011790": {
      "price": 124100
    },
    "001820": {
      "price": 109600
    }
  },
  "tech": {
    "128940": {
      "rsi": 53,
      "athAbs": 823333,
      "ath": "-50%"
    },
    "207940": {
      "rsi": 42,
      "athAbs": 1987000,
      "ath": "-35%"
    },
    "247540": {
      "rsi": 45,
      "athAbs": 584000,
      "ath": "-67%"
    },
    "267260": {
      "rsi": 50,
      "athAbs": 1430000,
      "ath": "-31%"
    },
    "329180": {
      "rsi": 55,
      "athAbs": 765000,
      "ath": "-16%"
    },
    "373220": {
      "rsi": 46,
      "athAbs": 629000,
      "ath": "-39%"
    },
    "bitcoin": {
      "ath": "-51%",
      "athAbs": 126080,
      "rsi": 29
    },
    "ethereum": {
      "ath": "-67%",
      "athAbs": 4946.05,
      "rsi": 24
    },
    "ripple": {
      "ath": "-69%",
      "athAbs": 3.65,
      "rsi": 19
    },
    "solana": {
      "ath": "-78%",
      "athAbs": 293.31,
      "rsi": 23
    },
    "dogecoin": {
      "ath": "-88%",
      "athAbs": 0.731578
    },
    "chainlink": {
      "ath": "-85%",
      "athAbs": 52.7,
      "rsi": 26
    },
    "ondo-finance": {
      "ath": "-84%",
      "athAbs": 2.14
    },
    "aave": {
      "ath": "-91%",
      "athAbs": 661.69,
      "rsi": 23
    },
    "filecoin": {
      "ath": "-100%",
      "athAbs": 236.84
    },
    "NVDA": {
      "rsi": 67,
      "athAbs": 236.54,
      "ath": "-14%"
    },
    "AMD": {
      "rsi": 75,
      "athAbs": 548.6823529411765,
      "ath": "-16%"
    },
    "ASML": {
      "rsi": 78,
      "athAbs": 1931.4588235294118,
      "ath": "-9%"
    },
    "MU": {
      "rsi": 90,
      "athAbs": 1089.2900390625,
      "ath": "-16%"
    },
    "SNDK": {
      "rsi": 61,
      "athAbs": 1861,
      "ath": "-9%"
    },
    "IREN": {
      "rsi": 55,
      "athAbs": 76.87000274658203,
      "ath": "-31%"
    },
    "VRT": {
      "rsi": 55,
      "athAbs": 379.935,
      "ath": "-26%"
    },
    "GEV": {
      "rsi": 50,
      "athAbs": 1181.95,
      "ath": "-26%"
    },
    "CRWV": {
      "rsi": 41,
      "athAbs": 187,
      "ath": "-48%"
    },
    "NBIS": {
      "rsi": 54,
      "athAbs": 278.84,
      "ath": "-21%"
    },
    "ASTS": {
      "rsi": 51,
      "athAbs": 133.86000061035156,
      "ath": "-34%"
    },
    "RKLB": {
      "rsi": 58,
      "athAbs": 151,
      "ath": "-30%"
    },
    "TSLA": {
      "rsi": 54,
      "athAbs": 498.83,
      "ath": "-23%"
    },
    "CRCL": {
      "rsi": 35,
      "athAbs": 298.99,
      "ath": "-73%"
    },
    "COIN": {
      "rsi": 38,
      "athAbs": 444.65,
      "ath": "-64%"
    },
    "SMR": {
      "rsi": 37,
      "athAbs": 57.42,
      "ath": "-83%"
    },
    "OKLO": {
      "rsi": 42,
      "athAbs": 193.84,
      "ath": "-71%"
    },
    "IONQ": {
      "rsi": 58,
      "athAbs": 103.23636363636363,
      "ath": "-44%"
    },
    "INFQ": {
      "rsi": 47,
      "athAbs": 21.280000686645508,
      "ath": "-35%"
    },
    "PLTR": {
      "rsi": 44,
      "athAbs": 207.52000427246094,
      "ath": "-36%"
    },
    "QQQ": {
      "rsi": 70,
      "athAbs": 748.6500244140625,
      "ath": "-6%"
    },
    "MRVL": {
      "rsi": 77,
      "athAbs": 324.20001220703125,
      "ath": "-20%"
    },
    "GLW": {
      "rsi": 84,
      "athAbs": 211.79,
      "ath": "-19%"
    },
    "CIEN": {
      "rsi": 71,
      "athAbs": 1057,
      "ath": "-59%"
    },
    "COHR": {
      "rsi": 80,
      "athAbs": 440,
      "ath": "-18%"
    },
    "LITE": {
      "rsi": 86,
      "athAbs": 1085.6800537109375,
      "ath": "-21%"
    },
    "AAOI": {
      "rsi": 78,
      "athAbs": 428.6315789473684,
      "ath": "-60%"
    },
    "000660": {
      "rsi": 78,
      "athAbs": 2407000,
      "ath": "-15%"
    },
    "005930": {
      "rsi": 77,
      "athAbs": 370000,
      "ath": "-18%"
    },
    "006400": {
      "rsi": 56,
      "athAbs": 828000,
      "ath": "-40%"
    },
    "096770": {
      "rsi": 46,
      "athAbs": 310181.78125,
      "ath": "-67%"
    },
    "066970": {
      "rsi": 50,
      "athAbs": 635909,
      "ath": "-80%"
    },
    "003670": {
      "rsi": 48,
      "athAbs": 746429,
      "ath": "-75%"
    },
    "042660": {
      "rsi": 57,
      "athAbs": 564918.875,
      "ath": "-80%"
    },
    "010140": {
      "rsi": 59,
      "athAbs": 42212.6484375,
      "ath": "-38%"
    },
    "012450": {
      "rsi": 57,
      "athAbs": 1655000,
      "ath": "-38%"
    },
    "064350": {
      "rsi": 55,
      "athAbs": 282000,
      "ath": "-33%"
    },
    "079550": {
      "rsi": 66,
      "athAbs": 1118000,
      "ath": "-29%"
    },
    "034020": {
      "rsi": 60,
      "athAbs": 151594.765625,
      "ath": "-40%"
    },
    "052690": {
      "rsi": 53,
      "athAbs": 198000,
      "ath": "-40%"
    },
    "068270": {
      "rsi": 48,
      "athAbs": 325235.46875,
      "ath": "-49%"
    },
    "009150": {
      "rsi": 82,
      "athAbs": 2192000,
      "ath": "-18%"
    },
    "011070": {
      "rsi": 72,
      "athAbs": 1788000,
      "ath": "-39%"
    },
    "011790": {
      "rsi": 52,
      "athAbs": 208000,
      "ath": "-40%"
    },
    "001820": {
      "rsi": 68,
      "athAbs": 172800,
      "ath": "-37%"
    }
  },
  "opts": {
    "BTC": {
      "maxPain": 62000,
      "pcr": 2.42,
      "expiry": "11JUN26"
    },
    "ETH": {
      "maxPain": 1675,
      "pcr": 0.89,
      "expiry": "11JUN26"
    },
    "NVDA": {
      "maxPain": 205,
      "pcr": 0.72
    },
    "AMD": {
      "maxPain": 482.5,
      "pcr": 1.05
    },
    "MU": {
      "maxPain": 920,
      "pcr": 1.82
    },
    "SNDK": {
      "maxPain": 1620,
      "pcr": 1.72
    },
    "IREN": {
      "maxPain": 56,
      "pcr": 1.92
    },
    "VRT": {
      "maxPain": 307.5,
      "pcr": 0.91
    },
    "ASTS": {
      "maxPain": 95,
      "pcr": 0.57
    },
    "RKLB": {
      "maxPain": 116,
      "pcr": 0.82
    },
    "TSLA": {
      "maxPain": 400,
      "pcr": 0.57
    },
    "CRCL": {
      "maxPain": 88,
      "pcr": 0.46
    },
    "COIN": {
      "maxPain": 160,
      "pcr": 0.56
    },
    "IONQ": {
      "maxPain": 57,
      "pcr": 0.87
    },
    "PLTR": {
      "maxPain": 138,
      "pcr": 0.54
    },
    "QQQ": {
      "maxPain": 709,
      "pcr": 1.34
    },
    "MRVL": {
      "maxPain": 257.5,
      "pcr": 1.17
    },
    "GLW": {
      "maxPain": 180,
      "pcr": 0.77
    },
    "CIEN": {
      "maxPain": 480,
      "pcr": 0.85
    },
    "COHR": {
      "maxPain": 380,
      "pcr": 1.61
    },
    "LITE": {
      "maxPain": 900,
      "pcr": 1.28
    },
    "AAOI": {
      "maxPain": 190,
      "pcr": 1.16
    }
  },
  "indices": {
    "KOSPI": {
      "price": 7730.82,
      "rsi": 72,
      "ath": "-13%"
    },
    "S&P 500": {
      "price": 7338.99,
      "rsi": 83,
      "ath": "-4%"
    },
    "Nasdaq": {
      "price": 25449.012,
      "rsi": 76,
      "ath": "-6%"
    },
    "Brent 유가": {
      "price": 92.8,
      "rsi": 57,
      "ath": "-37%"
    }
  },
  "macro": {
    "usdkrw": 1525,
    "cpi": "4.2%",
    "cpiDate": "2026-05"
  },
  "si": {
    "NVDA": {
      "si": "1.22%",
      "date": "05/29"
    },
    "AMD": {
      "si": "2.71%",
      "date": "05/29"
    },
    "ASML": {
      "si": "0.27%",
      "date": "05/29"
    },
    "MU": {
      "si": "3.34%",
      "date": "05/29"
    },
    "SNDK": {
      "si": "9.71%",
      "date": "05/29"
    },
    "IREN": {
      "si": "16.05%",
      "date": "05/29"
    },
    "VRT": {
      "si": "3.73%",
      "date": "05/29"
    },
    "GEV": {
      "si": "3.42%",
      "date": "05/29"
    },
    "CRWV": {
      "si": "18.19%",
      "date": "05/29"
    },
    "NBIS": {
      "si": "20.31%",
      "date": "05/29"
    },
    "ASTS": {
      "si": "18.39%",
      "date": "05/29"
    },
    "RKLB": {
      "si": "5.51%",
      "date": "05/29"
    },
    "TSLA": {
      "si": "2.30%",
      "date": "05/29"
    },
    "CRCL": {
      "si": "6.81%",
      "date": "05/29"
    },
    "COIN": {
      "si": "11.10%",
      "date": "05/29"
    },
    "SMR": {
      "si": "19.97%",
      "date": "05/29"
    },
    "OKLO": {
      "si": "18.02%",
      "date": "05/29"
    },
    "IONQ": {
      "si": "15.61%",
      "date": "05/29"
    },
    "PLTR": {
      "si": "3.23%",
      "date": "05/29"
    },
    "MRVL": {
      "si": "4.71%",
      "date": "05/29"
    },
    "GLW": {
      "si": "2.81%",
      "date": "05/29"
    },
    "CIEN": {
      "si": "5.01%",
      "date": "05/29"
    },
    "COHR": {
      "si": "4.70%",
      "date": "05/29"
    },
    "LITE": {
      "si": "14.54%",
      "date": "05/29"
    },
    "AAOI": {
      "si": "12.98%",
      "date": "05/29"
    }
  },
  "fund": {
    "128940": {
      "per": "46.52배",
      "fper": "40.26배"
    },
    "207940": {
      "per": "72.35배",
      "fper": "63.84배"
    },
    "267260": {
      "per": "86.05배",
      "fper": "71.71배"
    },
    "329180": {
      "per": "13.17배",
      "fper": "10.77배"
    },
    "000660": {
      "per": "8.51배",
      "fper": "6.28배"
    },
    "005930": {
      "per": "10.80배",
      "fper": "6.36배"
    },
    "042660": {
      "per": "18.08배",
      "fper": "15.50배"
    },
    "010140": {
      "per": "15.13배",
      "fper": "13.24배"
    },
    "012450": {
      "per": "19.92배",
      "fper": "17.79배"
    },
    "064350": {
      "per": "9.80배",
      "fper": "8.63배"
    },
    "079550": {
      "per": "22.05배",
      "fper": "20.21배"
    },
    "034020": {
      "per": "34.16배",
      "fper": "28.47배"
    },
    "052690": {
      "per": "40.84배",
      "fper": "35.74배"
    },
    "068270": {
      "per": "17.68배",
      "fper": "15.16배"
    },
    "009150": {
      "per": "28.13배",
      "fper": "23.44배"
    },
    "011070": {
      "per": "18.37배",
      "fper": "15.31배"
    },
    "001820": {
      "per": "32.24배",
      "fper": "28.37배"
    },
    "NVDA": {
      "per": "36.46배",
      "fper": "20.97배"
    },
    "AMD": {
      "per": "49.11배",
      "fper": "37.51배"
    },
    "ASML": {
      "per": "78.60배",
      "fper": "68.26배"
    },
    "MU": {
      "per": "19.87배",
      "fper": "17.88배"
    },
    "SNDK": {
      "per": "24.80배",
      "fper": "22.73배"
    },
    "VRT": {
      "per": "62.79배",
      "fper": "48.44배"
    },
    "GEV": {
      "per": "49.43배",
      "fper": "39.72배"
    },
    "NBIS": {
      "fper": "67.76배"
    },
    "TSLA": {
      "per": "82.77배",
      "fper": "65.35배"
    },
    "COIN": {
      "per": "31.75배",
      "fper": "27.78배"
    },
    "PLTR": {
      "per": "174.28배",
      "fper": "58.09배"
    },
    "MRVL": {
      "per": "90.08배",
      "fper": "60.35배"
    },
    "GLW": {
      "per": "39.22배",
      "fper": "24.40배"
    },
    "CIEN": {
      "per": "137.89배",
      "fper": "52.89배"
    },
    "COHR": {
      "per": "163.09배",
      "fper": "46.33배"
    },
    "LITE": {
      "per": "157.66배",
      "fper": "54.46배"
    }
  },
  "meta": {
    "cryptoCount": 9,
    "usCount": 27,
    "krCount": 24,
    "pricesGot": 60,
    "techGot": 60,
    "optsGot": 22,
    "indicesGot": 4,
    "siGot": 25,
    "fundGot": 33,
    "krSI": "수동(KRX 해외IP 차단)",
    "errors": []
  }
}