{
  "date": "2026-06-26",
  "updated": "2026-06-26T18:26:46.021Z",
  "phase": 2,
  "prices": {
    "128940": {
      "price": 366000
    },
    "207940": {
      "price": 1343000
    },
    "247540": {
      "price": 194000
    },
    "267260": {
      "price": 883000
    },
    "329180": {
      "price": 564000
    },
    "373220": {
      "price": 331500
    },
    "bitcoin": {
      "price": 59939,
      "chg": 0.58158
    },
    "ethereum": {
      "price": 1578.78,
      "chg": 0.50497
    },
    "ripple": {
      "price": 1.045,
      "chg": 0.51864
    },
    "solana": {
      "price": 72.67,
      "chg": 9.49665
    },
    "hyperliquid": {
      "price": 64.83,
      "chg": 2.42187
    },
    "dogecoin": {
      "price": 0.07547,
      "chg": 1.91876
    },
    "chainlink": {
      "price": 7.36,
      "chg": 1.67175
    },
    "sui": {
      "price": 0.696514,
      "chg": 2.34713
    },
    "uniswap": {
      "price": 3,
      "chg": 5.12888
    },
    "world-liberty-financial": {
      "price": 0.057901,
      "chg": -2.20791
    },
    "ondo-finance": {
      "price": 0.318831,
      "chg": 2.66183
    },
    "aave": {
      "price": 95.98,
      "chg": 14.65553
    },
    "filecoin": {
      "price": 0.753924,
      "chg": 3.5821
    },
    "pendle": {
      "price": 1.27,
      "chg": 1.72014
    },
    "zksync": {
      "price": 0.01035477,
      "chg": 0.90301
    },
    "centrifuge": {
      "price": 0.212893,
      "chg": 4.92417
    },
    "NVDA": {
      "price": 194.27
    },
    "AMD": {
      "price": 518.25
    },
    "ASML": {
      "price": 1781.12
    },
    "MU": {
      "price": 1145.397
    },
    "SNDK": {
      "price": 2126.08
    },
    "IREN": {
      "price": 47.595
    },
    "VRT": {
      "price": 304.82
    },
    "GEV": {
      "price": 1050.98
    },
    "CRWV": {
      "price": 95.415
    },
    "NBIS": {
      "price": 239.47
    },
    "ASTS": {
      "price": 72.467
    },
    "RKLB": {
      "price": 85.58
    },
    "TSLA": {
      "price": 383.74
    },
    "CRCL": {
      "price": 73.43
    },
    "COIN": {
      "price": 147.721
    },
    "SMR": {
      "price": 9.925
    },
    "OKLO": {
      "price": 50.645
    },
    "IONQ": {
      "price": 51.085
    },
    "INFQ": {
      "price": 13.57
    },
    "PLTR": {
      "price": 113.09
    },
    "QQQ": {
      "price": 710.43
    },
    "MRVL": {
      "price": 264.75
    },
    "GLW": {
      "price": 216.225
    },
    "CIEN": {
      "price": 477.235
    },
    "COHR": {
      "price": 384.3
    },
    "LITE": {
      "price": 813.335
    },
    "AAOI": {
      "price": 138.785
    },
    "AVGO": {
      "price": 369.25
    },
    "ANET": {
      "price": 156.86
    },
    "000660": {
      "price": 2673000
    },
    "005930": {
      "price": 339500
    },
    "006400": {
      "price": 455000
    },
    "096770": {
      "price": 89500
    },
    "066970": {
      "price": 98900
    },
    "003670": {
      "price": 160600
    },
    "042660": {
      "price": 98000
    },
    "010140": {
      "price": 23000
    },
    "012450": {
      "price": 1011000
    },
    "064350": {
      "price": 169800
    },
    "079550": {
      "price": 735000
    },
    "034020": {
      "price": 81100
    },
    "052690": {
      "price": 99900
    },
    "068270": {
      "price": 165900
    },
    "009150": {
      "price": 1993000
    },
    "011070": {
      "price": 931000
    },
    "011790": {
      "price": 104000
    },
    "001820": {
      "price": 130600
    }
  },
  "tech": {
    "128940": {
      "rsi": 49,
      "athAbs": 823333,
      "ath": "-56%"
    },
    "207940": {
      "rsi": 44,
      "athAbs": 1987000,
      "ath": "-32%"
    },
    "247540": {
      "rsi": 38,
      "athAbs": 584000,
      "ath": "-67%"
    },
    "267260": {
      "rsi": 45,
      "athAbs": 1430000,
      "ath": "-38%"
    },
    "329180": {
      "rsi": 47,
      "athAbs": 765000,
      "ath": "-26%"
    },
    "373220": {
      "rsi": 40,
      "athAbs": 629000,
      "ath": "-47%"
    },
    "bitcoin": {
      "ath": "-52%",
      "athAbs": 126080,
      "rsi": 37
    },
    "ethereum": {
      "ath": "-68%",
      "athAbs": 4946.05,
      "rsi": 36
    },
    "ripple": {
      "ath": "-71%",
      "athAbs": 3.65,
      "rsi": 29
    },
    "solana": {
      "ath": "-75%",
      "athAbs": 293.31,
      "rsi": 41
    },
    "hyperliquid": {
      "ath": "-15%",
      "athAbs": 76.7
    },
    "dogecoin": {
      "ath": "-90%",
      "athAbs": 0.731578,
      "rsi": 36
    },
    "chainlink": {
      "ath": "-86%",
      "athAbs": 52.7,
      "rsi": 26
    },
    "sui": {
      "ath": "-87%",
      "athAbs": 5.35
    },
    "uniswap": {
      "ath": "-93%",
      "athAbs": 44.92
    },
    "world-liberty-financial": {
      "ath": "-83%",
      "athAbs": 0.331336
    },
    "ondo-finance": {
      "ath": "-85%",
      "athAbs": 2.14
    },
    "aave": {
      "ath": "-85%",
      "athAbs": 661.69,
      "rsi": 23
    },
    "filecoin": {
      "ath": "-100%",
      "athAbs": 236.84
    },
    "pendle": {
      "ath": "-83%",
      "athAbs": 7.5
    },
    "zksync": {
      "ath": "-97%",
      "athAbs": 0.320983
    },
    "centrifuge": {
      "ath": "-90%",
      "athAbs": 2.19
    },
    "NVDA": {
      "rsi": 64,
      "athAbs": 236.54,
      "ath": "-18%"
    },
    "AMD": {
      "rsi": 81,
      "athAbs": 562.99,
      "ath": "-8%"
    },
    "ASML": {
      "rsi": 76,
      "athAbs": 1959.0400390625,
      "ath": "-9%"
    },
    "MU": {
      "rsi": 91,
      "athAbs": 1255,
      "ath": "-9%"
    },
    "SNDK": {
      "rsi": 59,
      "athAbs": 2354.39,
      "ath": "-10%"
    },
    "IREN": {
      "rsi": 49,
      "athAbs": 76.87000274658203,
      "ath": "-38%"
    },
    "VRT": {
      "rsi": 57,
      "athAbs": 379.935,
      "ath": "-20%"
    },
    "GEV": {
      "rsi": 62,
      "athAbs": 1181.95,
      "ath": "-11%"
    },
    "CRWV": {
      "rsi": 41,
      "athAbs": 187,
      "ath": "-49%"
    },
    "NBIS": {
      "rsi": 50,
      "athAbs": 299.86,
      "ath": "-20%"
    },
    "ASTS": {
      "rsi": 46,
      "athAbs": 133.86000061035156,
      "ath": "-46%"
    },
    "RKLB": {
      "rsi": 49,
      "athAbs": 151,
      "ath": "-43%"
    },
    "TSLA": {
      "rsi": 54,
      "athAbs": 498.83,
      "ath": "-23%"
    },
    "CRCL": {
      "rsi": 37,
      "athAbs": 298.99,
      "ath": "-75%"
    },
    "COIN": {
      "rsi": 37,
      "athAbs": 444.65,
      "ath": "-67%"
    },
    "SMR": {
      "rsi": 39,
      "athAbs": 57.42,
      "ath": "-83%"
    },
    "OKLO": {
      "rsi": 40,
      "athAbs": 193.84,
      "ath": "-74%"
    },
    "IONQ": {
      "rsi": 52,
      "athAbs": 103.23636363636363,
      "ath": "-51%"
    },
    "INFQ": {
      "rsi": 48,
      "athAbs": 21.280000686645508,
      "ath": "-36%"
    },
    "PLTR": {
      "rsi": 39,
      "athAbs": 207.52000427246094,
      "ath": "-46%"
    },
    "QQQ": {
      "rsi": 72,
      "athAbs": 748.6500244140625,
      "ath": "-5%"
    },
    "MRVL": {
      "rsi": 79,
      "athAbs": 329.8800048828125,
      "ath": "-20%"
    },
    "GLW": {
      "rsi": 89,
      "athAbs": 230.5,
      "ath": "-6%"
    },
    "CIEN": {
      "rsi": 77,
      "athAbs": 1057,
      "ath": "-55%"
    },
    "COHR": {
      "rsi": 83,
      "athAbs": 440,
      "ath": "-13%"
    },
    "LITE": {
      "rsi": 84,
      "athAbs": 1085.6800537109375,
      "ath": "-25%"
    },
    "AAOI": {
      "rsi": 76,
      "athAbs": 428.6315789473684,
      "ath": "-68%"
    },
    "AVGO": {
      "rsi": 61,
      "athAbs": 496.19480519480516,
      "ath": "-26%"
    },
    "ANET": {
      "rsi": 62,
      "athAbs": 179.8000030517578,
      "ath": "-13%"
    },
    "000660": {
      "rsi": 83,
      "athAbs": 2987000,
      "ath": "-11%"
    },
    "005930": {
      "rsi": 79,
      "athAbs": 374500,
      "ath": "-9%"
    },
    "006400": {
      "rsi": 53,
      "athAbs": 828000,
      "ath": "-45%"
    },
    "096770": {
      "rsi": 43,
      "athAbs": 310181.78125,
      "ath": "-71%"
    },
    "066970": {
      "rsi": 46,
      "athAbs": 635909,
      "ath": "-84%"
    },
    "003670": {
      "rsi": 45,
      "athAbs": 746429,
      "ath": "-78%"
    },
    "042660": {
      "rsi": 53,
      "athAbs": 564918.875,
      "ath": "-83%"
    },
    "010140": {
      "rsi": 54,
      "athAbs": 42212.6484375,
      "ath": "-46%"
    },
    "012450": {
      "rsi": 56,
      "athAbs": 1655000,
      "ath": "-39%"
    },
    "064350": {
      "rsi": 53,
      "athAbs": 282000,
      "ath": "-40%"
    },
    "079550": {
      "rsi": 64,
      "athAbs": 1118000,
      "ath": "-34%"
    },
    "034020": {
      "rsi": 56,
      "athAbs": 151594.765625,
      "ath": "-47%"
    },
    "052690": {
      "rsi": 50,
      "athAbs": 198000,
      "ath": "-50%"
    },
    "068270": {
      "rsi": 48,
      "athAbs": 325235.46875,
      "ath": "-49%"
    },
    "009150": {
      "rsi": 90,
      "athAbs": 2417000,
      "ath": "-18%"
    },
    "011070": {
      "rsi": 66,
      "athAbs": 1788000,
      "ath": "-48%"
    },
    "011790": {
      "rsi": 48,
      "athAbs": 208000,
      "ath": "-50%"
    },
    "001820": {
      "rsi": 78,
      "athAbs": 196800,
      "ath": "-34%"
    }
  },
  "opts": {
    "BTC": {
      "maxPain": 29,
      "pcr": 0.72,
      "pcrVol": 0.01,
      "maxPainTotal": 30,
      "pcrTotal": 0.33,
      "expiry": "7/17"
    },
    "ETH": {
      "maxPain": 4,
      "pcr": 0.37,
      "pcrVol": 0.18,
      "maxPainTotal": 16,
      "pcrTotal": 0.25,
      "expiry": "6/26"
    },
    "NVDA": {
      "maxPain": 197.5,
      "pcr": 0.53,
      "pcrVol": 0.69,
      "maxPainTotal": 185,
      "pcrTotal": 0.79,
      "expiry": "6/26"
    },
    "AMD": {
      "maxPain": 525,
      "pcr": 1.35,
      "pcrVol": 0.88,
      "maxPainTotal": 300,
      "pcrTotal": 1.11,
      "expiry": "6/26"
    },
    "ASML": {
      "maxPain": 1775,
      "pcr": 1.29,
      "pcrVol": 0.67,
      "maxPainTotal": 1615,
      "pcrTotal": 1.32,
      "expiry": "6/26"
    },
    "MU": {
      "maxPain": 1090,
      "pcr": 2.05,
      "pcrVol": 0.62,
      "maxPainTotal": 780,
      "pcrTotal": 1.4,
      "expiry": "6/26"
    },
    "SNDK": {
      "maxPain": 2045,
      "pcr": 1.98,
      "pcrVol": 0.81,
      "maxPainTotal": 1540,
      "pcrTotal": 1.52,
      "expiry": "6/26"
    },
    "IREN": {
      "maxPain": 53,
      "pcr": 2.3,
      "pcrVol": 2.01,
      "maxPainTotal": 50,
      "pcrTotal": 0.97,
      "expiry": "6/26"
    },
    "VRT": {
      "maxPain": 320,
      "pcr": 1.64,
      "pcrVol": 0.93,
      "maxPainTotal": 260,
      "pcrTotal": 1.03,
      "expiry": "6/26"
    },
    "GEV": {
      "maxPain": 1050,
      "pcr": 1.96,
      "pcrVol": 0.75,
      "maxPainTotal": 930,
      "pcrTotal": 1.29,
      "expiry": "6/26"
    },
    "CRWV": {
      "maxPain": 105,
      "pcr": 1.7,
      "pcrVol": 0.62,
      "maxPainTotal": 105,
      "pcrTotal": 0.94,
      "expiry": "6/26"
    },
    "NBIS": {
      "maxPain": 270,
      "pcr": 2.06,
      "pcrVol": 0.8,
      "maxPainTotal": 200,
      "pcrTotal": 1.17,
      "expiry": "6/26"
    },
    "ASTS": {
      "maxPain": 71,
      "pcr": 0.43,
      "pcrVol": 0.33,
      "maxPainTotal": 73,
      "pcrTotal": 0.44,
      "expiry": "6/26"
    },
    "RKLB": {
      "maxPain": 90,
      "pcr": 0.58,
      "pcrVol": 0.37,
      "maxPainTotal": 80,
      "pcrTotal": 0.73,
      "expiry": "6/26"
    },
    "TSLA": {
      "maxPain": 380,
      "pcr": 0.86,
      "pcrVol": 1.02,
      "maxPainTotal": 380,
      "pcrTotal": 0.72,
      "expiry": "6/26"
    },
    "CRCL": {
      "maxPain": 75,
      "pcr": 0.5,
      "pcrVol": 0.93,
      "maxPainTotal": 88,
      "pcrTotal": 0.78,
      "expiry": "6/26"
    },
    "COIN": {
      "maxPain": 157.5,
      "pcr": 0.66,
      "pcrVol": 0.76,
      "maxPainTotal": 170,
      "pcrTotal": 0.84,
      "expiry": "6/26"
    },
    "SMR": {
      "maxPain": 11,
      "pcr": 0.49,
      "pcrVol": 0.55,
      "maxPainTotal": 11,
      "pcrTotal": 0.51,
      "expiry": "6/26"
    },
    "OKLO": {
      "maxPain": 56,
      "pcr": 1.12,
      "pcrVol": 0.67,
      "maxPainTotal": 61,
      "pcrTotal": 0.67,
      "expiry": "6/26"
    },
    "IONQ": {
      "maxPain": 55,
      "pcr": 1.43,
      "pcrVol": 0.82,
      "maxPainTotal": 50,
      "pcrTotal": 1.03,
      "expiry": "6/26"
    },
    "INFQ": {
      "maxPain": 15,
      "pcr": 0.42,
      "pcrVol": 0.22,
      "maxPainTotal": 15,
      "pcrTotal": 0.36,
      "expiry": "7/17"
    },
    "PLTR": {
      "maxPain": 112,
      "pcr": 0.35,
      "pcrVol": 0.49,
      "maxPainTotal": 122,
      "pcrTotal": 0.89,
      "expiry": "6/26"
    },
    "QQQ": {
      "maxPain": 718,
      "pcr": 2.02,
      "pcrVol": 1.15,
      "maxPainTotal": 700,
      "pcrTotal": 1.46,
      "expiry": "6/26"
    },
    "PPIH": {
      "maxPain": 30,
      "pcr": 0.61,
      "pcrVol": 0,
      "maxPainTotal": 25,
      "pcrTotal": 0.35,
      "expiry": "7/17"
    },
    "MRVL": {
      "maxPain": 285,
      "pcr": 1.49,
      "pcrVol": 0.73,
      "maxPainTotal": 195,
      "pcrTotal": 1.13,
      "expiry": "6/26"
    },
    "GLW": {
      "maxPain": 200,
      "pcr": 0.97,
      "pcrVol": 0.7,
      "maxPainTotal": 165,
      "pcrTotal": 0.81,
      "expiry": "6/26"
    },
    "CIEN": {
      "maxPain": 450,
      "pcr": 0.7,
      "pcrVol": 0.24,
      "maxPainTotal": 447.5,
      "pcrTotal": 0.93,
      "expiry": "6/26"
    },
    "COHR": {
      "maxPain": 390,
      "pcr": 1.24,
      "pcrVol": 0.75,
      "maxPainTotal": 350,
      "pcrTotal": 1.23,
      "expiry": "6/26"
    },
    "LITE": {
      "maxPain": 855,
      "pcr": 0.97,
      "pcrVol": 0.29,
      "maxPainTotal": 835,
      "pcrTotal": 1.28,
      "expiry": "6/26"
    },
    "AAOI": {
      "maxPain": 150,
      "pcr": 1.45,
      "pcrVol": 0.43,
      "maxPainTotal": 140,
      "pcrTotal": 0.98,
      "expiry": "6/26"
    },
    "AVGO": {
      "maxPain": 390,
      "pcr": 0.81,
      "pcrVol": 0.94,
      "maxPainTotal": 370,
      "pcrTotal": 1.07,
      "expiry": "6/26"
    },
    "ANET": {
      "maxPain": 165,
      "pcr": 0.74,
      "pcrVol": 0.41,
      "maxPainTotal": 145,
      "pcrTotal": 0.89,
      "expiry": "6/26"
    },
    "SOL": {
      "maxPain": 2.5,
      "pcr": 0.02,
      "pcrVol": 0,
      "maxPainTotal": 2.5,
      "pcrTotal": 0.02,
      "expiry": "1/16"
    }
  },
  "indices": {
    "KOSPI": {
      "price": 8411.21,
      "rsi": 77,
      "ath": "-10%"
    },
    "S&P 500": {
      "price": 7362.86,
      "rsi": 83,
      "ath": "-3%"
    },
    "Nasdaq": {
      "price": 25338.83,
      "rsi": 78,
      "ath": "-7%"
    },
    "Brent 유가": {
      "price": 72.68,
      "rsi": 48,
      "ath": "-51%"
    }
  },
  "macro": {
    "usdkrw": 1536,
    "cpi": "4.2%",
    "cpiDate": "2026-05"
  },
  "si": {
    "NVDA": {
      "si": "1.29%",
      "date": "06/15"
    },
    "AMD": {
      "si": "2.88%",
      "date": "06/15"
    },
    "ASML": {
      "si": "0.43%",
      "date": "06/15"
    },
    "MU": {
      "si": "3.69%",
      "date": "06/15"
    },
    "SNDK": {
      "si": "11.50%",
      "date": "06/15"
    },
    "IREN": {
      "si": "18.63%",
      "date": "06/15"
    },
    "VRT": {
      "si": "3.91%",
      "date": "06/15"
    },
    "GEV": {
      "si": "3.93%",
      "date": "06/15"
    },
    "CRWV": {
      "si": "22.99%",
      "date": "06/15"
    },
    "NBIS": {
      "si": "23.35%",
      "date": "06/15"
    },
    "ASTS": {
      "si": "20.98%",
      "date": "06/15"
    },
    "RKLB": {
      "si": "5.94%",
      "date": "06/15"
    },
    "TSLA": {
      "si": "2.34%",
      "date": "06/15"
    },
    "CRCL": {
      "si": "9.90%",
      "date": "06/15"
    },
    "COIN": {
      "si": "12.19%",
      "date": "06/15"
    },
    "SMR": {
      "si": "22.83%",
      "date": "06/15"
    },
    "OKLO": {
      "si": "17.91%",
      "date": "06/15"
    },
    "IONQ": {
      "si": "13.60%",
      "date": "06/15"
    },
    "PLTR": {
      "si": "3.57%",
      "date": "06/15"
    },
    "MRVL": {
      "si": "5.26%",
      "date": "06/15"
    },
    "GLW": {
      "si": "3.12%",
      "date": "06/15"
    },
    "CIEN": {
      "si": "5.30%",
      "date": "06/15"
    },
    "COHR": {
      "si": "5.36%",
      "date": "06/15"
    },
    "LITE": {
      "si": "13.22%",
      "date": "06/15"
    },
    "AAOI": {
      "si": "13.24%",
      "date": "06/15"
    },
    "AVGO": {
      "si": "1.32%",
      "date": "06/15"
    },
    "ANET": {
      "si": "1.94%",
      "date": "06/15"
    }
  },
  "fund": {
    "128940": {
      "per": "41.37배",
      "fper": "35.80배"
    },
    "207940": {
      "per": "74.86배",
      "fper": "66.05배"
    },
    "267260": {
      "per": "77.06배",
      "fper": "64.22배"
    },
    "329180": {
      "per": "11.59배",
      "fper": "9.48배"
    },
    "000660": {
      "per": "11.10배",
      "fper": "8.19배"
    },
    "005930": {
      "per": "12.13배",
      "fper": "7.14배"
    },
    "042660": {
      "per": "16.08배",
      "fper": "13.78배"
    },
    "010140": {
      "per": "13.38배",
      "fper": "11.71배"
    },
    "012450": {
      "per": "19.54배",
      "fper": "17.44배"
    },
    "064350": {
      "per": "8.79배",
      "fper": "7.73배"
    },
    "079550": {
      "per": "20.51배",
      "fper": "18.80배"
    },
    "034020": {
      "per": "30.41배",
      "fper": "25.34배"
    },
    "052690": {
      "per": "34.37배",
      "fper": "30.08배"
    },
    "068270": {
      "per": "17.53배",
      "fper": "15.03배"
    },
    "009150": {
      "per": "31.06배",
      "fper": "25.88배"
    },
    "011070": {
      "per": "15.69배",
      "fper": "13.08배"
    },
    "001820": {
      "per": "38.41배",
      "fper": "33.80배"
    },
    "NVDA": {
      "per": "34.80배",
      "fper": "20.01배"
    },
    "AMD": {
      "per": "52.08배",
      "fper": "39.77배"
    },
    "ASML": {
      "per": "79.63배",
      "fper": "69.15배"
    },
    "MU": {
      "per": "21.06배",
      "fper": "18.95배"
    },
    "SNDK": {
      "per": "24.21배",
      "fper": "22.19배"
    },
    "VRT": {
      "per": "68.40배",
      "fper": "52.77배"
    },
    "GEV": {
      "per": "59.45배",
      "fper": "47.77배"
    },
    "NBIS": {
      "fper": "62.61배"
    },
    "TSLA": {
      "per": "88.67배",
      "fper": "70.00배"
    },
    "COIN": {
      "per": "29.54배",
      "fper": "25.85배"
    },
    "PLTR": {
      "per": "148.72배",
      "fper": "49.57배"
    },
    "MRVL": {
      "per": "85.71배",
      "fper": "57.43배"
    },
    "GLW": {
      "per": "51.79배",
      "fper": "32.22배"
    },
    "CIEN": {
      "per": "150.81배",
      "fper": "57.84배"
    },
    "COHR": {
      "per": "173.43배",
      "fper": "49.27배"
    },
    "LITE": {
      "per": "149.88배",
      "fper": "51.78배"
    },
    "AVGO": {
      "per": "91.69배",
      "fper": "36.68배"
    },
    "ANET": {
      "per": "53.64배",
      "fper": "40.23배"
    }
  },
  "meta": {
    "cryptoCount": 17,
    "usCount": 29,
    "krCount": 24,
    "pricesGot": 69,
    "techGot": 69,
    "optsGot": 33,
    "indicesGot": 4,
    "siGot": 27,
    "fundGot": 35,
    "krSI": "수동(KRX 해외IP 차단)",
    "errors": [
      "옵션 SOL: 만기 없음",
      "옵션 XRP: 만기 없음",
      "옵션 XRP(CBOE): HTTP 403"
    ]
  }
}